is_prime_gates/is_prime_gates.v
/*
    if input is prime (2, 3, 5, 7)
        return 1
    else
        return 0
*/

module is_prime_gates(
    input c,
    input b,
    input a,
    output P
  );

  assign P = (~c & b) | (c & a);

endmodule

is_prime_gates/is_prime_gates_tb.v
`include "is_prime_gates.v"

module is_prime_gates_tb();
    reg [2:0] cba;
    wire prime;

    is_prime_gates DUT_IPG(cba[2], cba[1], cba[0], prime);

    initial begin
        $dumpfile("is_prime_gates.vcd");
        $dumpvars(0,is_prime_gates_tb);

        cba = 3'd0;
        #1
        cba = 3'd1;
        #1
        cba = 3'd2;
        #1
        cba = 3'd3;
        #1
        cba = 3'd4;
        #1
        cba = 3'd5;
        #1
        cba = 3'd6;
        #1
        cba = 3'd7;
        #1
        cba = 3'd7;
    end

endmodule

is_prime_gates/is_prime_gates.vcd
$date
	Sun Sep 04 00:31:28 2022
$end
$version
	Icarus Verilog
$end
$timescale
	1s
$end
$scope module is_prime_gates_tb $end
$var wire 1 ! prime $end
$var reg 3 " cba [2:0] $end
$scope module DUT_IPG $end
$var wire 1 ! P $end
$var wire 1 # a $end
$var wire 1 $ b $end
$var wire 1 % c $end
$upscope $end
$upscope $end
$enddefinitions $end
#0
$dumpvars
0%
0$
0#
b0 "
0!
$end
#1
1#
b1 "
#2
1!
1$
0#
b10 "
#3
1#
b11 "
#4
0!
1%
0$
0#
b100 "
#5
1!
1#
b101 "
#6
0!
1$
0#
b110 "
#7
1!
1#
b111 "
